async_dag/__init__.py
async_dag/execution_result.py
async_dag/py.typed
async_dag/state.py
async_dag/task_manager.py
async_dag/task_node.py
async_dag-0.3.1.dist-info/METADATA
async_dag-0.3.1.dist-info/WHEEL
async_dag-0.3.1.dist-info/licenses/LICENSE
async_dag-0.3.1.dist-info/RECORD
