Metadata-Version: 2.4
Name: async-dag
Version: 0.3.1
Summary: A simple library for running complex DAG of async tasks while ensuring maximum possible parallelism
Author-email: Mayrom Rabinovich <nhruo123@gmail.com>
License-File: LICENSE
Requires-Python: >=3.12
